{
    "matches": [
        {
            "id": "502153917",
            "offset": 29.996808593,
            "timeskew": 7.1525574e-06,
            "frequencyskew": 0.0
        }
    ],
    "location": {
        "accuracy": 0.01
    },
    "timestamp": 1691633736880,
    "timezone": "Europe/Moscow",
    "track": {
        "layout": "5",
        "type": "MUSIC",
        "key": "47441886",
        "title": "Cultural Elite Sign - Up Sheet",
        "subtitle": "New Bomb Turks",
        "images": {
            "background": "https://is2-ssl.mzstatic.com/image/thumb/Music124/v4/59/44/7d/59447d0c-4032-262d-6507-ee05a48a5f23/0045778647965.png/400x400cc.jpg",
            "coverart": "https://is2-ssl.mzstatic.com/image/thumb/Music124/v4/59/44/7d/59447d0c-4032-262d-6507-ee05a48a5f23/0045778647965.png/400x400cc.jpg",
            "coverarthq": "https://is2-ssl.mzstatic.com/image/thumb/Music124/v4/59/44/7d/59447d0c-4032-262d-6507-ee05a48a5f23/0045778647965.png/400x400cc.jpg",
            "joecolor": "b:0b0404p:c1e81cs:90e23bt:9cbb17q:75b530"
        },
        "share": {
            "subject": "Cultural Elite Sign - Up Sheet - New Bomb Turks",
            "text": "Cultural Elite Sign - Up Sheet by New Bomb Turks",
            "href": "https://www.shazam.com/track/47441886/cultural-elite-sign-up-sheet",
            "image": "https://is2-ssl.mzstatic.com/image/thumb/Music124/v4/59/44/7d/59447d0c-4032-262d-6507-ee05a48a5f23/0045778647965.png/400x400cc.jpg",
            "twitter": "I used @Shazam to discover Cultural Elite Sign - Up Sheet by New Bomb Turks.",
            "html": "https://www.shazam.com/snippets/email-share/47441886?lang=en-US&country=GB",
            "snapchat": "https://www.shazam.com/partner/sc/track/47441886"
        },
        "hub": {
            "type": "APPLEMUSIC",
            "image": "https://images.shazam.com/static/icons/hub/ios/v5/applemusic_{scalefactor}.png",
            "actions": [
                {
                    "name": "apple",
                    "type": "applemusicplay",
                    "id": "1485036923"
                },
                {
                    "name": "apple",
                    "type": "uri",
                    "uri": "https://audio-ssl.itunes.apple.com/itunes-assets/AudioPreview115/v4/ce/42/b4/ce42b4cb-8e23-fe8b-918d-974e94513d81/mzaf_16621151748302788206.plus.aac.ep.m4a"
                }
            ],
            "options": [
                {
                    "caption": "OPEN IN",
                    "actions": [
                        {
                            "name": "hub:applemusic:deeplink",
                            "type": "applemusicopen",
                            "uri": "https://music.apple.com/gb/album/cultural-elite-sign-up-sheet/1485036479?i=1485036923&mttnagencyid=s2n&mttnsiteid=125115&mttn3pid=Apple-Shazam&mttnsub1=Shazam_ios&mttnsub2=5348615A-616D-3235-3830-44754D6D5973&itscg=30201&app=music&itsct=Shazam_ios"
                        },
                        {
                            "name": "hub:applemusic:deeplink",
                            "type": "uri",
                            "uri": "https://music.apple.com/gb/album/cultural-elite-sign-up-sheet/1485036479?i=1485036923&mttnagencyid=s2n&mttnsiteid=125115&mttn3pid=Apple-Shazam&mttnsub1=Shazam_ios&mttnsub2=5348615A-616D-3235-3830-44754D6D5973&itscg=30201&app=music&itsct=Shazam_ios"
                        }
                    ],
                    "beacondata": {
                        "type": "open",
                        "providername": "applemusic"
                    },
                    "image": "https://images.shazam.com/static/icons/hub/ios/v5/overflow-open-option_{scalefactor}.png",
                    "type": "open",
                    "listcaption": "Open in Apple Music",
                    "overflowimage": "https://images.shazam.com/static/icons/hub/ios/v5/applemusic-overflow_{scalefactor}.png",
                    "colouroverflowimage": false,
                    "providername": "applemusic"
                },
                {
                    "caption": "BUY",
                    "actions": [
                        {
                            "type": "uri",
                            "uri": "https://itunes.apple.com/gb/album/cultural-elite-sign-up-sheet/1485036479?i=1485036923&mttnagencyid=s2n&mttnsiteid=125115&mttn3pid=Apple-Shazam&mttnsub1=Shazam_ios&mttnsub2=5348615A-616D-3235-3830-44754D6D5973&itscg=30201&app=itunes&itsct=Shazam_ios"
                        }
                    ],
                    "beacondata": {
                        "type": "buy",
                        "providername": "itunes"
                    },
                    "image": "https://images.shazam.com/static/icons/hub/ios/v5/itunes-overflow-buy_{scalefactor}.png",
                    "type": "buy",
                    "listcaption": "Buy on iTunes",
                    "overflowimage": "https://images.shazam.com/static/icons/hub/ios/v5/itunes-overflow-buy_{scalefactor}.png",
                    "colouroverflowimage": false,
                    "providername": "itunes"
                }
            ],
            "providers": [
                {
                    "caption": "Open in Spotify",
                    "images": {
                        "overflow": "https://images.shazam.com/static/icons/hub/ios/v5/spotify-overflow_{scalefactor}.png",
                        "default": "https://images.shazam.com/static/icons/hub/ios/v5/spotify_{scalefactor}.png"
                    },
                    "actions": [
                        {
                            "name": "hub:spotify:searchdeeplink",
                            "type": "uri",
                            "uri": "spotify:search:Cultural%20Elite%20Sign%20-%20Up%20Sheet%20New%20Bomb%20Turks"
                        }
                    ],
                    "type": "SPOTIFY"
                },
                {
                    "caption": "Open in Deezer",
                    "images": {
                        "overflow": "https://images.shazam.com/static/icons/hub/ios/v5/deezer-overflow_{scalefactor}.png",
                        "default": "https://images.shazam.com/static/icons/hub/ios/v5/deezer_{scalefactor}.png"
                    },
                    "actions": [
                        {
                            "name": "hub:deezer:searchdeeplink",
                            "type": "uri",
                            "uri": "deezer-query://www.deezer.com/play?query=%7Btrack%3A%27Cultural+Elite+Sign+-+Up+Sheet%27%20artist%3A%27New+Bomb+Turks%27%7D"
                        }
                    ],
                    "type": "DEEZER"
                }
            ],
            "explicit": false,
            "displayname": "APPLE MUSIC"
        },
        "sections": [
            {
                "type": "SONG",
                "metapages": [
                    {
                        "image": "https://is2-ssl.mzstatic.com/image/thumb/Music124/v4/59/44/7d/59447d0c-4032-262d-6507-ee05a48a5f23/0045778647965.png/400x400cc.jpg",
                        "caption": "Cultural Elite Sign - Up Sheet"
                    }
                ],
                "tabname": "Song",
                "metadata": [
                    {
                        "title": "Album",
                        "text": "Scared Straight"
                    },
                    {
                        "title": "Label",
                        "text": "Epitaph"
                    },
                    {
                        "title": "Released",
                        "text": "1996"
                    }
                ]
            },
            {
                "type": "VIDEO",
                "tabname": "Video",
                "youtubeurl": "https://cdn.shazam.com/video/v3/-/GB/iphone/47441886/youtube/video?q=New+Bomb+Turks+%22Cultural+Elite+Sign+-+Up+Sheet%22"
            }
        ],
        "url": "https://www.shazam.com/track/47441886/cultural-elite-sign-up-sheet",
        "artists": [
            {
                "id": "42",
                "adamid": "259074720"
            }
        ],
        "isrc": "USEP40335104",
        "genres": {
            "primary": "Alternative"
        },
        "urlparams": {
            "{tracktitle}": "Cultural+Elite+Sign+-+Up+Sheet",
            "{trackartist}": "New+Bomb+Turks"
        },
        "myshazam": {
            "apple": {
                "actions": [
                    {
                        "name": "myshazam:apple",
                        "type": "uri",
                        "uri": "https://music.apple.com/gb/album/cultural-elite-sign-up-sheet/1485036479?i=1485036923&mttnagencyid=s2n&mttnsiteid=125115&mttn3pid=Apple-Shazam&mttnsub1=Shazam_ios&mttnsub2=5348615A-616D-3235-3830-44754D6D5973&itscg=30201&app=music&itsct=Shazam_ios"
                    }
                ]
            }
        },
        "highlightsurls": {
            "artisthighlightsurl": "https://cdn.shazam.com/video/v3/en-US/GB/iphone/259074720/highlights?affiliate=mttnagencyid%3Ds2n%26mttnsiteid%3D125115%26mttn3pid%3DApple-Shazam%26mttnsub1%3DShazam_ios%26mttnsub2%3D5348615A-616D-3235-3830-44754D6D5973%26itscg%3D30201%26app%3Dmusic%26itsct%3DShazam_ios"
        },
        "albumadamid": "1485036479"
    },
    "tagid": "7933C294-1A12-4691-9235-2A99B960A363"
}